{
	"fe_term" : "Summer 2020",
	"fe_exam" : "http://http://www.cs.ucf.edu/registration/exm/sum2020/FE-Aug20.pdf",
	"fe_exam_solutions" : "http://www.cs.ucf.edu/registration/exm/sum2020/FE-Aug20-Sol.pdf",
	"average_score_section_I" : "56.40%",
	"average_score_section_II" : "52.50%",
	"average_score_total" : "54.40%",
	"passing_line" : "60%",
	"number_of_passing" : "213",
	"number_of_students" : "457",
	"pass_rate" : "46.60%",
	"DS_A1" : "80%",
	"DS_A2" : "64.50%",
	"DS_A3" : "55.40%",
	"DS_B1" : "57.60%",
	"DS_B2" : "46.80%",
	"DS_B3" : "46.30%",
	"AA1" : "45.50%",
	"AA2" : "83%",
	"AA3" : "41.50%",
	"AB1" : "63.70%",
	"AB2" : "78.40%",
	"AB3" : "23.80%"
}